nimbus/__init__.py
nimbus/aws.py
nimbus/cli.py
nimbus/config.py
nimbus/errors.py
nimbus/logs.py
nimbus/saml.py
nimbus/utils.py
nimbus-0.0.3.dist-info/DESCRIPTION.rst
nimbus-0.0.3.dist-info/METADATA
nimbus-0.0.3.dist-info/RECORD
nimbus-0.0.3.dist-info/WHEEL
nimbus-0.0.3.dist-info/entry_points.txt
nimbus-0.0.3.dist-info/metadata.json
nimbus-0.0.3.dist-info/top_level.txt
