Metadata-Version: 2.0
Name: nimbus
Version: 0.0.3
Summary: Infrastructure tools for Amazon Web Services
Home-page: https://github.com/uscis/nimbus
Author: Andy Brody
Author-email: git@abrody.com
License: Public Domain
Platform: UNKNOWN
Classifier: Development Status :: 3 - Alpha
Classifier: Intended Audience :: Developers
Classifier: Intended Audience :: System Administrators
Classifier: License :: Public Domain
Classifier: Programming Language :: Python :: 2
Classifier: Programming Language :: Python :: 2.6
Classifier: Programming Language :: Python :: 2.7
Requires-Dist: atomicwrites (>=1.1.5,<2.0)
Requires-Dist: beautifulsoup4 (>=4.5.1,<5.0)
Requires-Dist: boto3 (>=1.4.0,<2.0)
Requires-Dist: click (>=6.6,<7.0)
Requires-Dist: pyyaml (>=3.11,<4.0)
Requires-Dist: requests (<3.0,>=2.11.1)
Requires-Dist: requests-kerberos (>=0.10.0,<1.0)
